__init__.py
numixery.py
numixery-1.0.0.dist-info/LICENSE
numixery-1.0.0.dist-info/METADATA
numixery-1.0.0.dist-info/WHEEL
numixery-1.0.0.dist-info/top_level.txt
numixery-1.0.0.dist-info/RECORD
